mplfinance/__init__.py
mplfinance/_arg_validators.py
mplfinance/_helpers.py
mplfinance/_kwarg_help.py
mplfinance/_mpf_warnings.py
mplfinance/_mplrcputils.py
mplfinance/_mplwraps.py
mplfinance/_panels.py
mplfinance/_styles.py
mplfinance/_utils.py
mplfinance/_version.py
mplfinance/_widths.py
mplfinance/original_flavor.py
mplfinance/plotting.py
mplfinance/_styledata/__init__.py
mplfinance/_styledata/binance.py
mplfinance/_styledata/blueskies.py
mplfinance/_styledata/brasil.py
mplfinance/_styledata/charles.py
mplfinance/_styledata/checkers.py
mplfinance/_styledata/classic.py
mplfinance/_styledata/default.py
mplfinance/_styledata/ibd.py
mplfinance/_styledata/kenan.py
mplfinance/_styledata/mike.py
mplfinance/_styledata/nightclouds.py
mplfinance/_styledata/sas.py
mplfinance/_styledata/starsandstripes.py
mplfinance/_styledata/yahoo.py
mplfinance-0.12.9b7.dist-info/LICENSE
mplfinance-0.12.9b7.dist-info/METADATA
mplfinance-0.12.9b7.dist-info/WHEEL
mplfinance-0.12.9b7.dist-info/top_level.txt
mplfinance-0.12.9b7.dist-info/RECORD
