Metadata-Version: 2.1
Name: mplfinance
Version: 0.12.9b7
Summary: Utilities for the visualization, and visual analysis, of financial data
Home-page: http://github.com/matplotlib/mplfinance
Author: MPL Developers
Author-email: matplotlib-users@python.org
Maintainer-email: dgoldfarb.github@gmail.com
License: BSD-style
Keywords: finance,candlestick,ohlc,market,investing,technical analysis
Platform: Cross platform (Linux
Platform: Mac OSX
Platform: Windows)
Classifier: Development Status :: 4 - Beta
Classifier: Programming Language :: Python :: 3
Classifier: Programming Language :: Python :: 3.6
Classifier: Programming Language :: Python :: 3.7
Classifier: Programming Language :: Python :: 3.8
Classifier: Programming Language :: Python :: 3.9
Classifier: Framework :: Matplotlib
Classifier: Intended Audience :: Developers
Classifier: Intended Audience :: Education
Classifier: Intended Audience :: Financial and Insurance Industry
Classifier: Intended Audience :: Science/Research
Classifier: License :: OSI Approved :: BSD License
Classifier: Topic :: Office/Business :: Financial
Classifier: Topic :: Office/Business :: Financial :: Investment
Classifier: Topic :: Scientific/Engineering :: Visualization
Classifier: Topic :: Scientific/Engineering :: Information Analysis
License-File: LICENSE
